noisytest/__init__.py
noisytest/model.py
noisytest/optimizer.py
noisytest/tunable.py
noisytest/ui.py
noisytest/pipeline/__init__.py
noisytest/pipeline/base.py
noisytest/pipeline/default.py
noisytest/preprocessor/__init__.py
noisytest/preprocessor/base.py
noisytest/preprocessor/data.py
noisytest/preprocessor/dct.py
noisytest/preprocessor/input_only.py
noisytest/preprocessor/spectrogram.py
noisytest/preprocessor/time_data_framer.py
noisytest/preprocessor/utils.py
noisytest/reader/__init__.py
noisytest/reader/dataset.py
noisytest/reader/experiment.py
noisytest/reader/meta_data.py
noisytest/reader/noise.py
noisytest-0.0.1.dist-info/LICENSE
noisytest-0.0.1.dist-info/METADATA
noisytest-0.0.1.dist-info/WHEEL
noisytest-0.0.1.dist-info/entry_points.txt
noisytest-0.0.1.dist-info/top_level.txt
noisytest-0.0.1.dist-info/RECORD
