Metadata-Version: 2.1
Name: noisytest
Version: 0.0.1
Summary: A noise-based failure detection tool for robot testing
Home-page: https://github.com/xifle/noisytest
Author: Felix Sygulla
Author-email: felix.sygulla@tum.de
License: MIT
Platform: UNKNOWN
Classifier: Programming Language :: Python :: 3
Classifier: License :: OSI Approved :: MIT License
Classifier: Operating System :: OS Independent
Requires-Python: >=3.6
Requires-Dist: dataclasses (>=0.7)
Requires-Dist: tensorflow (<3,>=2)
Requires-Dist: toml (>=0.10)
Requires-Dist: scikit-learn (>=0.22)
